COPYING
COPYRIGHT
INSTALL
LICENSE
MANIFEST.in
README.rst
setup.py
data/All Myzostoma sequence aligned MUSCLE.fas
data/COI_sequences_MUSCLE.fas
data/COI_sequences_MUSCLE_modified.fas
data/Example_bacteria.fas
data/Example_bacteria2.fas
data/Fungi_ITS_for_FastaChar.fas
data/Pontohedyle_spp_18S__with_names_broken.fas
data/Pontohedyle_spp_18S__with_names_for_FastaChar.fas
data/Pontohedyle_spp_18S__with_names_for_FastaChar_no_question_marks.fas
data/Pontohedyle_spp_with_names_for_FastaChar.fas
data/Pontohedyle_spp_with_names_for_FastaChar_ammended.fas
data/Streptococcus_pneumoniae_full_genomes.fas
data/coi_test.txt
data/coi_test.xls
data/its.xls
data/mockup.fas
data/quiddich.fas
examples/analysis_example.py
fastachar/__init__.py
fastachar/fasta_doc.py
fastachar/fasta_io.py
fastachar/fasta_logic.py
fastachar/tkgui.py
fastachar.egg-info/PKG-INFO
fastachar.egg-info/SOURCES.txt
fastachar.egg-info/dependency_links.txt
fastachar.egg-info/entry_points.txt
fastachar.egg-info/requires.txt
fastachar.egg-info/top_level.txt