Metadata-Version: 2.1
Name: fastachar
Version: 0.2.4
Summary: A simple program with GUI to compare dna sequences
Home-page: http://cubic-l.science/fastachar.html
Author: Lucas Merckelbach
Author-email: lucas.merckelbach@hzg.de
License: UNKNOWN
Platform: UNKNOWN
Classifier: Development Status :: 4 - Beta
Classifier: Environment :: Console
Classifier: Intended Audience :: Science/Research
Classifier: License :: OSI Approved :: GNU General Public License v3 (GPLv3)
Classifier: Operating System :: MacOS :: MacOS X
Classifier: Operating System :: Microsoft :: Windows
Classifier: Operating System :: POSIX
Classifier: Programming Language :: Python
Classifier: Topic :: Scientific/Engineering
